[
  {
    "theme": "總則與基本原則",
    "articles": [
      "第一條",
      "第二條",
      "第三條",
      "第四條",
      "第五條",
      "第七條",
      "第八條",
      "第九條",
      "第十條",
      "第十一條",
      "第十一條之一"
    ]
  },
  {
    "theme": "採購金額與級距",
    "articles": [
      "第十二條",
      "第十三條",
      "第十四條"
    ]
  },
  {
    "theme": "招標方式與程序",
    "articles": [
      "第十八條",
      "第十九條",
      "第二十條",
      "第二十一條",
      "第二十二條",
      "第二十三條",
      "第二十四條",
      "第二十五條",
      "第二十七條",
      "第二十八條",
      "第二十九條",
      "第三十三條",
      "第三十四條",
      "第三十五條",
      "第三十七條",
      "第三十八條",
      "第三十九條",
      "第四十一條",
      "第四十二條",
      "第四十三條"
    ]
  },
  {
    "theme": "招標文件與公告",
    "articles": [
      "第四十四條",
      "第四十五條",
      "第四十七條",
      "第四十八條",
      "第四十九條"
    ]
  },
  {
    "theme": "押標金與保證金",
    "articles": [
      "第三十條",
      "第三十一條",
      "第三十二條"
    ]
  },
  {
    "theme": "決標原則",
    "articles": [
      "第五十二條",
      "第五十三條",
      "第五十四條",
      "第五十五條",
      "第五十七條",
      "第五十八條",
      "第五十九條"
    ]
  },
  {
    "theme": "履約管理",
    "articles": [
      "第七十條之一"
    ]
  },
  {
    "theme": "驗收作業",
    "articles": [
      "第七十一條",
      "第七十二條",
      "第七十三條",
      "第七十三條之一"
    ]
  },
  {
    "theme": "異議與申訴",
    "articles": [
      "第七十四條",
      "第七十五條",
      "第七十七條",
      "第七十八條",
      "第七十九條",
      "第八十一條",
      "第八十二條",
      "第八十三條",
      "第八十四條"
    ]
  },
  {
    "theme": "調解與仲裁",
    "articles": [
      "第八十五條",
      "第八十五條之一",
      "第八十五條之二",
      "第八十五條之三",
      "第八十五條之四"
    ]
  },
  {
    "theme": "罰則與不良廠商停權",
    "articles": [
      "第八十七條",
      "第八十八條",
      "第八十九條",
      "第九十一條",
      "第九十二條",
      "第九十三條",
      "第九十三條之一",
      "第九十四條",
      "第九十五條",
      "第九十七條",
      "第九十八條",
      "第九十九條"
    ]
  },
  {
    "theme": "附則與其他規定",
    "articles": [
      "第一百十條",
      "第一百十一條",
      "第一百十二條",
      "第一百十三條",
      "第一百十四條"
    ]
  }
]